sls_enum/__init__.py
sls_enum/main.py
sls_enum-0.3.0.dist-info/METADATA
sls_enum-0.3.0.dist-info/WHEEL
sls_enum-0.3.0.dist-info/entry_points.txt
sls_enum-0.3.0.dist-info/RECORD
